LICENSE
waybar_openweathermap/__init__.py
waybar_openweathermap-1.0.3.dist-info/LICENSE
waybar_openweathermap-1.0.3.dist-info/METADATA
waybar_openweathermap-1.0.3.dist-info/WHEEL
waybar_openweathermap-1.0.3.dist-info/entry_points.txt
waybar_openweathermap-1.0.3.dist-info/RECORD
