Metadata-Version: 2.1
Name: waybar-openweathermap
Version: 1.0.3
Summary: Weather info widget for Waybar, from OpenWeatherMap.org
Home-page: https://github.com/MrTango/waybar-openweathermap
License: MIT
Keywords: waybar,sway,swaywm,wayland
Author: Maik Derstappen - Derico
Requires-Python: >=3.6,<4.0
Classifier: Development Status :: 5 - Production/Stable
Classifier: Environment :: Console
Classifier: License :: OSI Approved :: MIT License
Classifier: Operating System :: OS Independent
Classifier: Programming Language :: Python :: 3
Classifier: Programming Language :: Python :: 3.6
Classifier: Programming Language :: Python :: 3.7
Classifier: Programming Language :: Python :: 3.8
Classifier: Programming Language :: Python :: 3.9
Classifier: Programming Language :: Python :: 3.10
Classifier: Programming Language :: Python :: 3.11
Classifier: Programming Language :: Python :: 3.12
Classifier: Programming Language :: Python :: 3.13
Classifier: Topic :: Desktop Environment :: Window Managers
Requires-Dist: geopy (>=2.2.0,<3.0.0)
Requires-Dist: requests (>=2.28.1,<3.0.0)
Project-URL: Repository, https://github.com/MrTango/waybar-openweathermap
